opentf/agent/__init__.py
opentf/agent/agent.py
nightly_opentf_agent-1.8.0.dev223.dist-info/LICENSE
nightly_opentf_agent-1.8.0.dev223.dist-info/METADATA
nightly_opentf_agent-1.8.0.dev223.dist-info/WHEEL
nightly_opentf_agent-1.8.0.dev223.dist-info/entry_points.txt
nightly_opentf_agent-1.8.0.dev223.dist-info/top_level.txt
nightly_opentf_agent-1.8.0.dev223.dist-info/RECORD
