Metadata-Version: 2.1
Name: nightly-opentf-agent
Version: 1.8.0.dev223
Summary: OpenTestFactory Orchestrator Agent
Home-page: https://opentestfactory.org/guides/agent.html
Author: Martin Lafaix
Author-email: mlafaix@henix.com
Maintainer: Henix
Maintainer-email: opentestfactory@henix.com
License: Apache Software License (https://www.apache.org/licenses/LICENSE-2.0)
Platform: UNKNOWN
Classifier: Development Status :: 4 - Beta
Classifier: Programming Language :: Python :: 3
Classifier: Operating System :: OS Independent
Classifier: Topic :: Software Development :: Libraries
Classifier: License :: OSI Approved :: Apache Software License
Requires-Python: >= 3.7.0
License-File: LICENSE
Requires-Dist: requests (>=2.25)
